hat/mariner/transport/connection.py
hat/mariner/server/__init__.py
hat/mariner/server/main.py
hat/mariner/__init__.py
hat/mariner/json_schema_repo.json
hat/mariner/transport/__init__.py
hat/mariner/transport/common.py
hat/mariner/transport/encoder.py
hat/mariner/server/__main__.py
hat/mariner/common.py
hat/mariner/client.py
hat/mariner/server/server.py
hat_mariner-0.9.5.dist-info/LICENSE
hat_mariner-0.9.5.dist-info/entry_points.txt
hat_mariner-0.9.5.dist-info/METADATA
hat_mariner-0.9.5.dist-info/WHEEL
hat_mariner-0.9.5.dist-info/RECORD
