Metadata-Version: 2.1
Name: hat-mariner
Version: 0.9.5
Summary: Hat mariner
License: Apache-2.0
Provides-Extra: dev
Requires-Dist: appdirs ~=1.4.4
Requires-Dist: hat-aio ~=0.7.12
Requires-Dist: hat-drivers ~=0.9.1
Requires-Dist: hat-event ~=0.9.36
Requires-Dist: hat-json ~=0.6.2
Requires-Dist: hat-monitor ~=0.8.19
Requires-Dist: hat-util ~=0.6.19
Requires-Dist: hat-doit ~=0.16.2; extra == 'dev'
Requires-Dist: sphinxcontrib-programoutput >=0.17; extra == 'dev'
Requires-Python: >=3.10
Project-URL: Homepage, http://hat-open.com
Project-URL: Repository, https://github.com/hat-open/hat-mariner.git
Project-URL: Documentation, http://hat-mariner.hat-open.com
